kindaxml-0.1.1.dist-info/METADATA
kindaxml-0.1.1.dist-info/WHEEL
kindaxml-0.1.1.dist-info/licenses/LICENSE
kindaxml.libs/libgcc_s-98a1ef30.so.1
kindaxml/__init__.py
kindaxml/__init__.pyi
kindaxml/_kindaxml_rs.cpython-312-x86_64-linux-musl.so
kindaxml/py.typed
kindaxml-0.1.1.dist-info/RECORD
