Metadata-Version: 2.4
Name: kindaxml
Version: 0.1.1
License-File: LICENSE
Summary: Add your description here
Home-Page: https://github.com/soraxas/kindaxml
Requires-Python: >=3.12
